airbyte_ai_zendesk_support/__init__.py
airbyte_ai_zendesk_support/connector.py
airbyte_ai_zendesk_support/connector.yaml
airbyte_ai_zendesk_support/models.py
airbyte_ai_zendesk_support/types.py
airbyte_ai_zendesk_support/_vendored/__init__.py
airbyte_ai_zendesk_support/_vendored/connector_sdk/__init__.py
airbyte_ai_zendesk_support/_vendored/connector_sdk/auth_strategies.py
airbyte_ai_zendesk_support/_vendored/connector_sdk/auth_template.py
airbyte_ai_zendesk_support/_vendored/connector_sdk/config_loader.py
airbyte_ai_zendesk_support/_vendored/connector_sdk/constants.py
airbyte_ai_zendesk_support/_vendored/connector_sdk/exceptions.py
airbyte_ai_zendesk_support/_vendored/connector_sdk/extensions.py
airbyte_ai_zendesk_support/_vendored/connector_sdk/http_client.py
airbyte_ai_zendesk_support/_vendored/connector_sdk/secrets.py
airbyte_ai_zendesk_support/_vendored/connector_sdk/types.py
airbyte_ai_zendesk_support/_vendored/connector_sdk/utils.py
airbyte_ai_zendesk_support/_vendored/connector_sdk/validation.py
airbyte_ai_zendesk_support/_vendored/connector_sdk/executor/__init__.py
airbyte_ai_zendesk_support/_vendored/connector_sdk/executor/hosted_executor.py
airbyte_ai_zendesk_support/_vendored/connector_sdk/executor/local_executor.py
airbyte_ai_zendesk_support/_vendored/connector_sdk/executor/models.py
airbyte_ai_zendesk_support/_vendored/connector_sdk/http/__init__.py
airbyte_ai_zendesk_support/_vendored/connector_sdk/http/config.py
airbyte_ai_zendesk_support/_vendored/connector_sdk/http/exceptions.py
airbyte_ai_zendesk_support/_vendored/connector_sdk/http/protocols.py
airbyte_ai_zendesk_support/_vendored/connector_sdk/http/response.py
airbyte_ai_zendesk_support/_vendored/connector_sdk/http/adapters/__init__.py
airbyte_ai_zendesk_support/_vendored/connector_sdk/http/adapters/httpx_adapter.py
airbyte_ai_zendesk_support/_vendored/connector_sdk/logging/__init__.py
airbyte_ai_zendesk_support/_vendored/connector_sdk/logging/logger.py
airbyte_ai_zendesk_support-0.18.16.dist-info/METADATA
airbyte_ai_zendesk_support-0.18.16.dist-info/WHEEL
airbyte_ai_zendesk_support-0.18.16.dist-info/RECORD
